textutils_plus/__init__.py
textutils_plus/count.py
textutils_plus/reverse.py
textutils_plus-0.1.0.dist-info/LICENSE
textutils_plus-0.1.0.dist-info/METADATA
textutils_plus-0.1.0.dist-info/WHEEL
textutils_plus-0.1.0.dist-info/top_level.txt
textutils_plus-0.1.0.dist-info/RECORD
