Metadata-Version: 2.1
Name: textutils-plus
Version: 0.1.0
Summary: A small library for counting words and reversing text.
Author-email: Your Name <you@example.com>
License: 
Project-URL: Homepage, https://github.com/yourusername/textutils-plus
Requires-Python: >=3.7
License-File: LICENSE
